[
    {
        "thumbnail": "../../assets/posts/post-11-03-2019.jpg",
        "http": "https://haein.info/",
        "date": "11-03-2019",
        "internationalizations": [
            {
                "language": "en",
                "title": "Lorem ipsum",
                "description": "Lorem ipsum dolor sit amet, consectetur adipiscing elit, sed do eiusmod tempor incididunt ut labore et dolore magna aliqua. Urna nunc id cursus metus aliquam."
            },
            {
                "language": "pt",
                "title": "A fórmula de matriz 2D anti-deslocamento.",
                "description": "Você já pensou na <b>relação matemática</b> entre as<i> colunas</i> e as <i>linhas</i> de uma matriz bidimensional <i>(matriz 2d)</i>? Essa estrutura de dados oculta uma <b>fórmula de localização de dados</b> que me ajudou a evitar a <i>complexidade de tempo de O(n²)</i>, que é um cenário péssimo, transformando-a em uma <i>complexidade do tempo constante - O(1)</i>. Uma explicação completa, com casos de teste reais e testes de unidade, está esperando por você."
            }
        ]
    },
    {
        "thumbnail": "../../assets/posts/post-05-21-2016.jpg",
        "http": "https://haein.info/",
        "date": "05-21-2016",
        "internationalizations": [
            {
                "language": "en",
                "title": "Lorem ipsum",
                "description": "Lorem ipsum dolor sit amet, consectetur adipiscing elit, sed do eiusmod tempor incididunt ut labore et dolore magna aliqua. Urna nunc id cursus metus aliquam."
            },
            {
                "language": "pt",
                "title": "Notificação de usuário no Android - <i>Componente de código aberto</i>.",
                "description": "Um componente completo para quem precisa de um baralho de cartas dinâmicas com gráficos interativos para Android. Muito parecido com o que encontramos em <i> Tinder </i>. Código-fonte totalmente aberto para alterações e melhorias."
            }
        ]
    }
]